memonster/__init__.py
memonster/memanagers.py
memonster/memtypes.py
memonster/metamem.py
memonster/utils.py
memonster-0.4.2.dist-info/LICENSE
memonster-0.4.2.dist-info/WHEEL
memonster-0.4.2.dist-info/METADATA
memonster-0.4.2.dist-info/RECORD
